ctk_colorpicker_plus/__init__.py
ctk_colorpicker_plus/color_utils.py
ctk_colorpicker_plus/color_wheel.png
ctk_colorpicker_plus/ctk_color_picker.py
ctk_colorpicker_plus/ctk_color_picker_widget.py
ctk_colorpicker_plus/target.png
ctk_colorpicker_plus-0.1.1.dist-info/licenses/LICENSE
ctk_colorpicker_plus-0.1.1.dist-info/METADATA
ctk_colorpicker_plus-0.1.1.dist-info/WHEEL
ctk_colorpicker_plus-0.1.1.dist-info/top_level.txt
ctk_colorpicker_plus-0.1.1.dist-info/RECORD
