Metadata-Version: 2.4
Name: ctk-colorpicker-plus
Version: 0.1.1
Summary: Enhanced CustomTkinter color picker widget with bug fixes, hex input, and improved reticle/slider behavior.
Author-email: Phil Rice <overman@z-studios.com>
License: MIT License
Project-URL: Homepage, https://github.com/calusasoft/ctk-colorpicker-plus
Project-URL: Repository, https://github.com/calusasoft/ctk-colorpicker-plus
Project-URL: Issues, https://github.com/calusasoft/ctk-colorpicker-plus/issues
Keywords: customtkinter,tkinter,colorpicker,color wheel,gui
Classifier: Development Status :: 5 - Production/Stable
Classifier: Environment :: Win32 (MS Windows)
Classifier: Environment :: MacOS X
Classifier: Environment :: X11 Applications
Classifier: Intended Audience :: Developers
Classifier: License :: OSI Approved :: MIT License
Classifier: Operating System :: OS Independent
Classifier: Programming Language :: Python
Classifier: Programming Language :: Python :: 3
Classifier: Programming Language :: Python :: 3.8
Classifier: Programming Language :: Python :: 3.9
Classifier: Programming Language :: Python :: 3.10
Classifier: Programming Language :: Python :: 3.11
Classifier: Programming Language :: Python :: 3.12
Classifier: Topic :: Software Development :: User Interfaces
Classifier: Topic :: Software Development :: Libraries :: Python Modules
Requires-Python: >=3.8
License-File: LICENSE
Requires-Dist: customtkinter>=5.2
Requires-Dist: Pillow>=10.0
Dynamic: license-file
